promptogen/__init__.py
promptogen/model/__init__.py
promptogen/model/dataclass.py
promptogen/model/llm.py
promptogen/model/prompt.py
promptogen/model/prompt_interceptor.py
promptogen/model/prompt_runner.py
promptogen/model/prompt_transformer.py
promptogen/model/reasoning_extractor.py
promptogen/model/value_formatter.py
promptogen/prompt_collection/__init__.py
promptogen/prompt_collection/predefined_prompts.py
promptogen/prompt_collection/prompt_collection.py
promptogen/prompt_collection/prompts/__init__.py
promptogen/prompt_collection/prompts/dict_translator.py
promptogen/prompt_collection/prompts/prompt_creator.py
promptogen/prompt_collection/prompts/prompt_example_creator.py
promptogen/prompt_collection/prompts/prompt_optimizer.py
promptogen/prompt_collection/prompts/python_code_generator.py
promptogen/prompt_collection/prompts/text_categorizer.py
promptogen/prompt_collection/prompts/text_condenser.py
promptogen/prompt_collection/prompts/text_summarizer.py
promptogen/prompt_formatter/__init__.py
promptogen/prompt_formatter/json_formatter.py
promptogen/prompt_formatter/key_value_formatter.py
promptogen/prompt_formatter/prompt_formatter.py
promptogen/prompt_formatter/text_formatter.py
promptogen/prompt_interceptor/__init__.py
promptogen/prompt_interceptor/translation_interceptor.py
promptogen/prompt_tool/__init__.py
promptogen/prompt_tool/transformation/__init__.py
promptogen/prompt_tool/transformation/prompt_with_reasoning.py
promptogen/prompt_tool/translation/dict_translator.py
promptogen/prompt_tool/understanding/__init__.py
promptogen/prompt_tool/understanding/llm_reasoning_extractor.py
promptogen/py.typed
promptogen-0.0.6.dist-info/LICENSE
promptogen-0.0.6.dist-info/METADATA
promptogen-0.0.6.dist-info/WHEEL
promptogen-0.0.6.dist-info/RECORD
